{
  "bool_plex_movie_support": "Soporte de agente de película de Plex (Añadir temas al agente de película de Plex actualizado)",
  "bool_plex_series_support": "Soporte de agente de la Serie Plex (Añadir temas al agente actualizado de la Serie Plex)",
  "bool_overwrite_plex_provided_themes": "Sobrescribir temas proporcionados por Plex",
  "bool_prefer_mp4a_codec": "Preferir MP4A AAC Codec (mejora la compatibilidad con dispositivos Apple)",
  "bool_remove_unused_theme_songs": "Eliminar canciones de tema no utilizadas (libera espacio en el directorio de metadatos de Plex)",
  "bool_remove_unused_art": "Eliminar el arte no utilizado (se aplica a las colecciones, libera espacio en el directorio de metadatos de Plex)",
  "bool_remove_unused_posters": "Eliminar carteles no utilizados (se aplica a las colecciones, libera espacio en el directorio de metadatos de Plex)",
  "bool_auto_update_items": "Actualizar automáticamente los elementos (sólo elementos cambiados o faltantes en ThemerrDB)",
  "bool_auto_update_movie_themes": "Actualizar temas de película durante la actualización automática",
  "bool_auto_update_tv_themes": "Actualizar temas de serie de tv durante la actualización automática",
  "bool_auto_update_collection_themes": "Actualizar temas de la colección durante la actualización automática",
  "bool_update_collection_metadata_plex_movie": "Actualizar metadatos de colección para agente de película de Plex (Actualizaciones de póster, arte y resumen)",
  "bool_update_collection_metadata_legacy": "Actualizar metadatos de colección para agentes heredados (Actualizaciones de póster, arte y resumen)",
  "int_update_themes_interval": "Intervalo para la tarea de actualización automática, en minutos (min: 15)",
  "int_update_database_cache_interval": "Intervalo para la tarea de actualización de la caché de base de datos, en minutos (min: 15)",
  "int_plexapi_plexapi_timeout": "Tiempo de espera de PlexAPI, en segundos (min: 1)",
  "int_plexapi_upload_retries_max": "Máx. Reintentos, entero (min: 0)",
  "int_plexapi_upload_threads": "Multiprocesamiento de hilos, entero (min: 1)",
  "str_youtube_cookies": "Cookies de YouTube (formato JSON)",
  "enum_webapp_locale": "Web UI Locale",
  "str_webapp_http_host": "Dirección de host Web UI (requiere reiniciar Plex Media Server)",
  "int_webapp_http_port": "Puerto Web UI (requiere reiniciar Plex Media Server)",
  "bool_webapp_log_werkzeug_messages": "Registrar todos los mensajes del servidor web (requiere reiniciar Plex Media Server)",
  "bool_migrate_locked_themes": "Migrafiar temas de < v0.3.0 (Si utilizaste Themerr antes de v0.3.0, establece esto en True)",
  "bool_migrate_locked_collection_fields": "Migrafiar metadatos de colección de < v0.3.0 (Si usaste Themerr antes de v0.3.0, establezca esto en True)",
  "bool_ignore_locked_fields": "Ignorar campos bloqueados (Siempre subir medios, incluso si los campos están bloqueados)"
}
