{
  "bool_plex_movie_support": "Supporto agente Plex Movie (Aggiungi temi all'agente Plex Movie aggiornato)",
  "bool_plex_series_support": "Supporto agente Plex Series (Aggiungi temi all'agente Plex Series aggiornato)",
  "bool_overwrite_plex_provided_themes": "Sovrascrivi i temi forniti da Plex",
  "bool_prefer_mp4a_codec": "Preferire MP4A AAC Codec (Migliora la compatibilità con i dispositivi Apple)",
  "bool_remove_unused_theme_songs": "Rimuove i brani del tema inutilizzati (libera spazio nella directory dei metadati di Plex)",
  "bool_remove_unused_art": "Rimuovi l'arte inutilizzata (si applica alle collezioni, libera spazio nella tua directory dei metadati di Plex)",
  "bool_remove_unused_posters": "Rimuovi i poster inutilizzati (si applica alle collezioni, libera spazio nella directory dei metadati di Plex)",
  "bool_auto_update_items": "Aggiorna automaticamente gli elementi (solo gli elementi cambiati o mancanti in ThemerrDB)",
  "bool_auto_update_movie_themes": "Aggiorna i temi del film durante l'aggiornamento automatico",
  "bool_auto_update_tv_themes": "Aggiorna temi TV durante l'aggiornamento automatico",
  "bool_auto_update_collection_themes": "Aggiorna i temi della collezione durante l'aggiornamento automatico",
  "bool_update_collection_metadata_plex_movie": "Aggiorna i metadati della collezione per Plex Movie agent (Aggiorna poster, arte e riepilogo)",
  "bool_update_collection_metadata_legacy": "Aggiorna i metadati della raccolta per gli agenti legacy (Aggiorna poster, arte e riepilogo)",
  "int_update_themes_interval": "Intervallo per attività di aggiornamento automatico, in minuti (min: 15)",
  "int_update_database_cache_interval": "Intervallo per il compito di aggiornamento della cache del database, in minuti (min: 15)",
  "int_plexapi_plexapi_timeout": "Timeout PlexAPI, in secondi (min: 1)",
  "int_plexapi_upload_retries_max": "Max Retries, intero (min: 0)",
  "int_plexapi_upload_threads": "Discussioni di elaborazione multiple, intere (min: 1)",
  "str_youtube_cookies": "Cookie su YouTube (formato JSON)",
  "enum_webapp_locale": "Web UI Locale",
  "str_webapp_http_host": "Indirizzo Host UI Web (richiede il riavvio di Plex Media Server)",
  "int_webapp_http_port": "Porta UI Web (richiede il riavvio di Plex Media Server)",
  "bool_webapp_log_werkzeug_messages": "Registra tutti i messaggi del server web (richiede il riavvio di Plex Media Server)",
  "bool_migrate_locked_themes": "Migra temi da < v0.3.0 (Se hai usato Themerr prima di v0.3.0, impostalo su True)",
  "bool_migrate_locked_collection_fields": "Migra i metadati della collezione da < v0.3.0 (Se hai usato Themerr prima di v0.3.0, impostalo su True)",
  "bool_ignore_locked_fields": "Ignora i campi bloccati (carica sempre il supporto, anche se i campi sono bloccati)"
}
